{"hash":"6fd5ff102fffd499608eb2622e8b5bdbefbb833a","data":{"drupalNodeEvent":{"id":"2d4835f8-9791-44bb-ba07-1e6739eb811e","title":"The Crisis of China’s Investment Environment","field_starting_time":"2020-09-16T16:30:00+00:00","field_speakers":{"processed":"<p>Lily Wu(China Prosper Group)</p>\n"},"field_organizers":{"processed":"<p>Fairbank Center for Chinese Studies</p>\n"},"field_event_mode":"Online","field_event_language":"English","field_event_record":true,"field_event_category":"Talk","field_time_zone":"","field_event_website":{"uri":"https://fairbank.fas.harvard.edu/events/webinar-lily-wu-the-crisis-of-chinas-investment-environment/"},"field_registration":true,"field_event_venue":"","field_description":null}},"context":{}}