{"hash":"f79f035379a10fc9dcd7103ca417129f6e2c461b","data":{"drupalNodeEvent":{"id":"84aaf0f2-073d-46b1-83c8-a6f2da6e1435","title":"A Public Lecture  - How Do We Think about History: The Intellectual Inquiry of Thinking about Historiography in Asia","field_starting_time":"2022-02-28T02:30:00+00:00","field_speakers":{"processed":"<p>趙軼峰教授 (東北師範大學亞洲文明研究院院長；《古代文明》執行主編)</p>\n"},"field_organizers":{"processed":"<p>HKBU Department of History and Modern History Research Centre</p>\n"},"field_event_mode":"Online","field_event_language":"Putonghua","field_event_record":false,"field_event_category":"Talk","field_time_zone":"Asia/Hong_Kong","field_event_website":{"uri":"https://histweb.hkbu.edu.hk/upload/activitie/291/download/61d6b5e1f3c77.pdf"},"field_registration":false,"field_event_venue":"","field_description":null}},"context":{}}