{"hash":"4958713077a2639c2cc6010af89986def5f36e0a","data":{"drupalNodeEvent":{"id":"81aab9f4-a79e-424b-855e-ac43a165a598","title":"Parental Dictates: Marriage Sorting and Social Mobility in Imperial China, 1614-1854","field_starting_time":"2025-04-30T02:30:00+00:00","field_speakers":{"processed":"<p>Dr. Xizi Luo (Postdoctoral Fellow, Institute of Historical Research and Economic History Society University of Oxford)<br />\nXizi Luo is a scholar of economic history with broad interests in institutions, inequality, culture and ideas, political economy, and development economics. She earned her PhD in Economic History from the London School of Economics in August 2024. She is currently a Postdoctoral Fellow at the Institute of Historical Research and Economic History Society, based at the University of Oxford (2024–2025). Her doctoral dissertation explored the interaction between social mobility and institutions in shaping inequality in premodern Chinese society. Her current research investigates the long-term political and economic impact of Wang Yangming’s philosophy, contributing to interdisciplinary debates on the role of ideas in institutional and developmental trajectories.</p>\n"},"field_organizers":{"processed":"<p><span style=\"font-size:12pt\"><span style=\"font-family:&quot;Times New Roman&quot;,serif\">Hong Kong Institute for the Humanities and Social Sciences, The University of Hong Kong</span></span></p>\n"},"field_event_mode":"In-person","field_event_language":"English","field_event_record":false,"field_event_category":"Talk","field_time_zone":"Asia/Hong_Kong","field_event_website":{"uri":"https://www.hkihss.hku.hk/en/events/parental-dictates-marriage-sorting-and-social-mobility-in-imperial-china-1614-1854/"},"field_registration":true,"field_event_venue":"Lecture Hall, G/F, May Hall, The University of Hong Kong","field_description":{"processed":"<p>This study explores marriage dynamics in Qing-era China (1614-1854) using a unique nationwide dataset derived from civil examination records. The findings indicate an increase in female bargaining power and a pattern of women ”marrying up” due to an unbalanced sex ratio driven by son preference, discouraged remarriage, and the prevalence of concubinage. The research quantitatively demonstrates a high level of assortative mating in Chinese marriages, highlighting a strong correlation between the social standings of fathers and fathers-in-law, and emphasizing the role of marriage in transmitting intergenerational advantages. The study underscores marriage as a crucial mechanism for elite perpetuation, particularly in mitigating the risks of downward mobility. Significant associations are identified between the social standings of the father-in-law, groom, and subsequent generations, emphasizing the importance of parentally arranged marriages and maternal support in lineage continuity.</p>\n"}}},"context":{}}