{"hash":"1a507a36edcf1f0cf031bda32cfe09bba846721f","data":{"drupalNodeEvent":{"id":"b64696b6-bdda-4133-b74e-adc6a842c192","title":"Dam Diplomacy? Chinese Dam Building and Water Disputes in Asia","field_starting_time":"2021-09-17T13:00:00+00:00","field_speakers":{"processed":"<p>Selina Ho, Carla Freeman, Jessica Liao</p>\n"},"field_organizers":{"processed":"<p>BU Center for the Study of Asia</p>\n"},"field_event_mode":"Online","field_event_language":"English","field_event_record":true,"field_event_category":"Talk","field_time_zone":"","field_event_website":{"uri":"https://www.bu.edu/asian/2021/09/06/assessing-chinas-belt-and-road-initiative-asia-dam-diplomacy-chinese-dam-building-and-water-disputes-in-asia-sept-17-2021/"},"field_registration":true,"field_event_venue":"","field_description":null}},"context":{}}