{"hash":"898f5738789534c2b6b6010af89986def5f36e0a","data":{"drupalNodeEvent":{"id":"4f16cf2c-8201-480e-ae47-475deeec7a1f","title":"清前期甘肅官茶引與地方財政 ","field_starting_time":"2022-10-13T06:30:00+00:00","field_speakers":{"processed":"<p><span class=\"blue2\"><span class=\"gray\">賴惠敏教授（中研院近代史研究所所研究員）</span></span></p>\n"},"field_organizers":{"processed":"<p>中央研究院近代史研究所</p>\n"},"field_event_mode":"Hybrid","field_event_language":"mandarin ","field_event_record":false,"field_event_category":"","field_time_zone":"Asia/Taipei","field_event_website":{"uri":"https://www.mh.sinica.edu.tw/UcEvent00_Detail.aspx?eventID=1861&tableName=Event&tmid=21&mid=57"},"field_registration":false,"field_event_venue":"","field_description":{"processed":"<p>本研究利用《清代軍機處滿文熬茶檔》、《軍機處雍正朝滿文議覆檔譯編》、《康熙朝滿文硃批奏摺全譯》、《雍正朝滿文硃批奏摺全譯》、《雍正朝漢文硃批奏摺彙編》、中研院史語所藏《清代內閣大庫原藏明清檔案》，國立故宮博物院藏《清代宮中檔奏摺及軍機處檔摺件》、中國第一歷史檔案館藏《宮中硃批奏摺．財政類》等有百餘件檔案，分為三個章節：康雍時期甘肅的官茶引、乾隆年間積貯茶封的處理，以及茶引與地方財政的關係，分析茶課經費支應地方用度。</p>\n"}}},"context":{}}