{"hash":"df1608ad6a8ac808311cf8fc0e2bee7d482d79bd","data":{"drupalNodeEvent":{"id":"afb15934-e235-425d-a7b3-7db426b4796c","title":"Africa and China: Structural Changes and Economic Transformation","field_starting_time":"2021-10-20T13:00:00+00:00","field_speakers":{"processed":"<p>Yan Wang</p>\n"},"field_organizers":{"processed":"<p>Boston University Global Development Policy Center</p>\n"},"field_event_mode":"Online","field_event_language":"English","field_event_record":true,"field_event_category":"Talk","field_time_zone":"","field_event_website":{"uri":"https://www.bu.edu/gdp/events/?eid=257452"},"field_registration":true,"field_event_venue":"","field_description":{"processed":"<p>In a chapter for a World Bank September 2021 publication, Justin Lin and Yan Wang argue African countries should adopt development strategies around their comparative advantages and have credible and capable governments to oversee these strategies to achieve dynamic growth and economic transformation. Lin and Wang&#039;s empirical analysis found that 78 percent of China financed and completed projects in soft and hard infrastructures have addressed Africa‘s bottlenecks, thereby creating public assets, which could generate income and jobs. These public assets could also provide a cushion during times of financial crisis. On Wednesday, October 20, join Yan Wang, Senior Academic Researcher at the Boston University Global Development Policy Center, for a discussion on China and Africa&#039;s investment history and how they can rethink their development cooperation post-pandemic. This webinar is part of the Fall 2021 Global China Research Colloquium.</p>\n"}}},"context":{}}