{"hash":"c11415cc77598fc96d65ccb469f6d605edbfcf81","data":{"drupalNodeEvent":{"id":"562e7909-2c64-4307-92ce-670d6b43a38e","title":"China’s Role in Global Finance","field_starting_time":"2021-04-14T16:30:00+00:00","field_speakers":{"processed":"<p>Eswar Prasad (Cornell University)</p>\n"},"field_organizers":{"processed":"<p>Harvard University Fairbank Center For Chinese Studies</p>\n"},"field_event_mode":"Online","field_event_language":"","field_event_record":true,"field_event_category":"Talk","field_time_zone":"","field_event_website":{"uri":"https://fairbank.fas.harvard.edu/events/eswar-prasad-critical-issues-confronting-china-lecture-series/"},"field_registration":true,"field_event_venue":"","field_description":{"processed":"<p>This lecture will discuss China’s economic prospects, policies, and reforms, and their implications for its role in international finance. The lecture will cover China’s economy, financial markets, and the renminbi, and also touch upon the country’s new digital currency.</p>\n"}}},"context":{}}