{"hash":"52069f86e8fad682b88cbe9aea8fda7f35c07914","data":{"drupalNodeEvent":{"id":"0003f15a-8243-4804-a1d6-cdf875e01ae7","title":"最新的联邦假日与美国的两次“重建”","field_starting_time":"2021-07-25T00:30:00+00:00","field_speakers":{"processed":"<p>王希(University of Pennsylvania),洪朝辉(Fordham University),刘亚伟</p>\n"},"field_organizers":{"processed":"<p>University Forum</p>\n"},"field_event_mode":"Online","field_event_language":"mandarin","field_event_record":true,"field_event_category":"Talk","field_time_zone":"","field_event_website":{"uri":"https://www.youtube.com/channel/UChnTf6-SqrxZWafWNuIiNjA"},"field_registration":true,"field_event_venue":"","field_description":{"processed":"<p>2021年6月17日，美国总统拜登签署了国会两院通过的《6月19日独立日法》(Juneteenth National Independence Day Act)，将6月19日定为最新的美国联邦假日，以纪念美国内战（1861-1865）中奴隶制的终结、最后一批奴隶获得解放的日子。奴隶制如何引爆了美国内战？谁在内战中解放了奴隶？获得解放的奴隶为何在（第一次）重建（1863-1877）结束之后丧失了平等的公民地位和权利？他们又如何重新获得平等的公民地位和权利？20世纪50、60年代的民权运动为何被称为是“第二次重建”？本讲座将围绕上述问题展开叙述，勾画黑白美国人在19-20世纪为废除奴隶制和种族歧视而进行的艰苦卓绝的漫长斗争经历，比较两次“重建”的进程与得失，并讨论当前美国种族关系面临的挑战。搜索“大学沙龙”YouTube账号，参加线上讲座。</p>\n"}}},"context":{}}